Workbook

Sheet Parametros
A1: PARAMETROS DEL CALCULO
A2: Ningun porcentaje se escribe dentro de una formula: todas las hojas apuntan a estas celdas.
A3: Parametro | B3: Valor | C3: Fuente | D3: Fecha de consulta
A4: RMV | B4: 1230 | C4: D.S. de la RMV, vigente desde el 01/10/2026 | D4: 29/10/2026
A5: Tasa asignacion familiar | B5: 0.1 | C5: Ley 25129 (10% de la RMV) | D5: 29/10/2026
A6: Asignacion familiar (S/) | B6: =ROUND(B4*B5,2) | C6: Calculada: RMV x 10% | D6: 29/10/2026
A7: Tasa ONP | B7: 0.13 | C7: D.L. 19990 | D7: 29/10/2026
A8: Tasa EsSalud | B8: 0.09 | C8: Ley 26790 (la paga el empleador) | D8: 29/10/2026
A9: Factor horas extras 25% | B9: 1.25 | C9: Normas de jornada y sobretiempo | D9: 29/10/2026
A10: Factor horas extras 35% | B10: 1.35 | C10: Normas de jornada y sobretiempo | D10: 29/10/2026
A11: Dias del mes | B11: 30 | C11: Divisor legal para el sueldo diario | D11: 29/10/2026
A12: Horas de jornada | B12: 8 | C12: Divisor legal para el valor hora | D12: 29/10/2026
A13: AFP Ejemplo (valores de prueba del enunciado)
A14: AFP Ejemplo - fondo | B14: 0.1 | C14: Valores de prueba. Con datos reales, usar los publicados por la SBS | D14: 29/10/2026
A15: AFP Ejemplo - comision | B15: 0.016 | C15: Valores de prueba. Con datos reales, usar los publicados por la SBS | D15: 29/10/2026
A16: AFP Ejemplo - seguro | B16: 0.0135 | C16: Valores de prueba. Con datos reales, usar los publicados por la SBS | D16: 29/10/2026
A19: CONVENCIONES DE REDONDEO
A20: Cada concepto se redondea a 2 decimales con ROUND() y luego se suman.
A21: Los intermedios (valor hora, sueldo diario) NO se redondean.
A22: ROUND() redondea medio hacia arriba: 0.005 sube.
A23: El valor hora sale del SUELDO BASICO, no del sueldo computable.
A24: La asignacion familiar es un monto fijo: no se prorratea por dias laborados.
A25: EsSalud lo paga el empleador: nunca se resta del neto del trabajador.

Sheet Boleta
A1: BOLETA DE EJEMPLO
A2: Cambia solo las celdas amarillas. Todo lo demas son formulas.
A3: DATOS DE ENTRADA
A4: Sueldo basico (S/) | B4: 3000
A5: Dias laborados (1 a 30) | B5: 30
A6: Tiene hijos (SI / NO) | B6: SI
A7: Sistema de pensiones (ONP / AFP) | B7: AFP
A8: Horas extras al 25% | B8: 4
A9: Horas extras al 35% | B9: 4
A10: Adelantos (S/) | B10: 200
A12: Valor hora (intermedio, sin redondear) | B12: =B4/Parametros!$B$11/Parametros!$B$12
A14: REMUNERACIONES
A15: Sueldo computable | B15: =ROUND(B4/Parametros!$B$11*B5,2)
A16: Asignacion familiar | B16: =IF(UPPER(B6)="SI",Parametros!$B$6,0)
A17: Horas extras 25% | B17: =ROUND($B$12*Parametros!$B$9*B8,2)
A18: Horas extras 35% | B18: =ROUND($B$12*Parametros!$B$10*B9,2)
A19: Total remuneraciones | B19: =SUM(B15:B18)
A21: RETENCIONES / DESCUENTOS
A22: ONP | B22: =IF(UPPER(B7)="ONP",ROUND($B$19*Parametros!$B$7,2),0)
A23: AFP fondo | B23: =IF(UPPER(B7)="AFP",ROUND($B$19*Parametros!$B$14,2),0)
A24: AFP comision | B24: =IF(UPPER(B7)="AFP",ROUND($B$19*Parametros!$B$15,2),0)
A25: AFP seguro | B25: =IF(UPPER(B7)="AFP",ROUND($B$19*Parametros!$B$16,2),0)
A26: Adelantos | B26: =ROUND(B10,2)
A27: Total descuentos | B27: =SUM(B22:B26)
A29: NETO A PAGAR | B29: =B19-B27
A31: APORTACIONES DEL EMPLEADOR
A32: EsSalud (9%) | B32: =ROUND($B$19*Parametros!$B$8,2)
A33: No se descuenta al trabajador: es costo del empleador.

Sheet Casos
A1: CASOS DE PRUEBA
A2: La fila Diferencia debe dar 0.00 en los cuatro casos: ese es el control cruzado contra la app.
B3: Caso 1 | C3: Caso 2 | D3: Caso 3 | E3: Caso 4
A4: Sueldo basico | B4: 2500 | C4: 1800 | D4: 3000 | E4: 4200
A5: Dias laborados | B5: 30 | C5: 27 | D5: 30 | E5: 24
A6: Tiene hijos | B6: NO | C6: SI | D6: SI | E6: SI
A7: Sistema | B7: ONP | C7: ONP | D7: AFP | E7: AFP
A8: Horas extras 25% | B8: 0 | C8: 0 | D8: 4 | E8: 2
A9: Horas extras 35% | B9: 0 | C9: 0 | D9: 4 | E9: 2
A10: Adelantos | B10: 0 | C10: 0 | D10: 200 | E10: 100
A12: Valor hora | B12: =B4/Parametros!$B$11/Parametros!$B$12 | C12: =C4/Parametros!$B$11/Parametros!$B$12 | D12: =D4/Parametros!$B$11/Parametros!$B$12 | E12: =E4/Parametros!$B$11/Parametros!$B$12
A13: Sueldo computable | B13: =ROUND(B4/Parametros!$B$11*B5,2) | C13: =ROUND(C4/Parametros!$B$11*C5,2) | D13: =ROUND(D4/Parametros!$B$11*D5,2) | E13: =ROUND(E4/Parametros!$B$11*E5,2)
A14: Asignacion familiar | B14: =IF(UPPER(B6)="SI",Parametros!$B$6,0) | C14: =IF(UPPER(C6)="SI",Parametros!$B$6,0) | D14: =IF(UPPER(D6)="SI",Parametros!$B$6,0) | E14: =IF(UPPER(E6)="SI",Parametros!$B$6,0)
A15: Horas extras 25% | B15: =ROUND(B$12*Parametros!$B$9*B8,2) | C15: =ROUND(C$12*Parametros!$B$9*C8,2) | D15: =ROUND(D$12*Parametros!$B$9*D8,2) | E15: =ROUND(E$12*Parametros!$B$9*E8,2)
A16: Horas extras 35% | B16: =ROUND(B$12*Parametros!$B$10*B9,2) | C16: =ROUND(C$12*Parametros!$B$10*C9,2) | D16: =ROUND(D$12*Parametros!$B$10*D9,2) | E16: =ROUND(E$12*Parametros!$B$10*E9,2)
A17: Total remuneraciones | B17: =SUM(B13:B16) | C17: =SUM(C13:C16) | D17: =SUM(D13:D16) | E17: =SUM(E13:E16)
A18: ONP | B18: =IF(UPPER(B7)="ONP",ROUND(B$17*Parametros!$B$7,2),0) | C18: =IF(UPPER(C7)="ONP",ROUND(C$17*Parametros!$B$7,2),0) | D18: =IF(UPPER(D7)="ONP",ROUND(D$17*Parametros!$B$7,2),0) | E18: =IF(UPPER(E7)="ONP",ROUND(E$17*Parametros!$B$7,2),0)
A19: AFP fondo | B19: =IF(UPPER(B7)="AFP",ROUND(B$17*Parametros!$B$14,2),0) | C19: =IF(UPPER(C7)="AFP",ROUND(C$17*Parametros!$B$14,2),0) | D19: =IF(UPPER(D7)="AFP",ROUND(D$17*Parametros!$B$14,2),0) | E19: =IF(UPPER(E7)="AFP",ROUND(E$17*Parametros!$B$14,2),0)
A20: AFP comision | B20: =IF(UPPER(B7)="AFP",ROUND(B$17*Parametros!$B$15,2),0) | C20: =IF(UPPER(C7)="AFP",ROUND(C$17*Parametros!$B$15,2),0) | D20: =IF(UPPER(D7)="AFP",ROUND(D$17*Parametros!$B$15,2),0) | E20: =IF(UPPER(E7)="AFP",ROUND(E$17*Parametros!$B$15,2),0)
A21: AFP seguro | B21: =IF(UPPER(B7)="AFP",ROUND(B$17*Parametros!$B$16,2),0) | C21: =IF(UPPER(C7)="AFP",ROUND(C$17*Parametros!$B$16,2),0) | D21: =IF(UPPER(D7)="AFP",ROUND(D$17*Parametros!$B$16,2),0) | E21: =IF(UPPER(E7)="AFP",ROUND(E$17*Parametros!$B$16,2),0)
A22: Adelantos | B22: =ROUND(B10,2) | C22: =ROUND(C10,2) | D22: =ROUND(D10,2) | E22: =ROUND(E10,2)
A23: Total descuentos | B23: =SUM(B18:B22) | C23: =SUM(C18:C22) | D23: =SUM(D18:D22) | E23: =SUM(E18:E22)
A24: NETO A PAGAR | B24: =B17-B23 | C24: =C17-C23 | D24: =D17-D23 | E24: =E17-E23
A25: EsSalud (empleador) | B25: =ROUND(B$17*Parametros!$B$8,2) | C25: =ROUND(C$17*Parametros!$B$8,2) | D25: =ROUND(D$17*Parametros!$B$8,2) | E25: =ROUND(E$17*Parametros!$B$8,2)
A27: CONTROL CRUZADO
A28: Neto esperado | B28: 2175 | C28: 1516.41 | D28: 2631.73 | E28: 3011.17
A29: Diferencia (debe ser 0.00) | B29: =ROUND(B24-B28,2) | C29: =ROUND(C24-C28,2) | D29: =ROUND(D24-D28,2) | E29: =ROUND(E24-E28,2)
A31: Casos 1, 2 y 3: el neto esperado viene con respuesta en el enunciado.
A32: Caso 4: no trae respuesta oficial, lo evalua el docente. El valor de la fila 28 es el que produce la app.
A34: CASO PROPIO (sueldo de una oferta laboral real)
A35: Alumno
A36: Sueldo de la oferta (S/)
A37: Enlace de la oferta
A38: Fecha de consulta
A39: % del bruto que llega al trabajador

Sheet Explicacion
A1: EXPLICACION DE CADA FORMULA
A2: Escrita para alguien que no sabe contabilidad. Los ejemplos usan el Caso 3: sueldo 3,000.00, 30 dias, con hijos, AFP Ejemplo, 4 horas al 25%, 4 al 35%, adelanto 200.00.
A4: Concepto | B4: Formula en la hoja | C4: En palabras | D4: Ejemplo numerico (Caso 3)
A5: Valor hora | B5: Sueldo basico / 30 / 8 | C5: Cuanto vale una hora de trabajo. Se divide el sueldo entre los 30 dias del mes y luego entre las 8 horas de la jornada. Este numero NO se redondea, porque es un paso intermedio. | D5: 3,000 / 30 / 8 = 12.50
A6: Sueldo computable | B6: ROUND(Sueldo basico / 30 x Dias laborados, 2) | C6: La parte del sueldo que corresponde a los dias que el trabajador realmente trabajo. Si trabajo el mes completo, es igual al sueldo basico. Las faltas ya estan reflejadas aqui. | D6: 3,000 / 30 x 30 = 3,000.00
A7: Asignacion familiar | B7: IF(Tiene hijos = "SI", 10% de la RMV, 0) | C7: Monto fijo que recibe el trabajador que tiene hijos. Es el 10% de la remuneracion minima vital. Se paga completo aunque haya trabajado menos dias: NO se prorratea. | D7: 10% x 1,230 = 123.00
A8: Horas extras 25% | B8: ROUND(Valor hora x 1.25 x Horas, 2) | C8: Las primeras horas trabajadas despues de la jornada se pagan con 25% de recargo. Por eso se multiplica por 1.25, no por 0.25: el 1 es la hora normal y el 0.25 es el recargo. | D8: 12.50 x 1.25 x 4 = 62.50
A9: Horas extras 35% | B9: ROUND(Valor hora x 1.35 x Horas, 2) | C9: Las horas siguientes se pagan con 35% de recargo, por la misma logica. | D9: 12.50 x 1.35 x 4 = 67.50
A10: Total remuneraciones | B10: SUM(los cuatro conceptos de arriba) | C10: Todo lo que el trabajador gano en el mes, antes de cualquier descuento. Es la base sobre la que se calculan la pension y EsSalud. | D10: 3,000.00 + 123.00 + 62.50 + 67.50 = 3,253.00
A11: ONP | B11: IF(Sistema = "ONP", ROUND(Total remuneraciones x 13%, 2), 0) | C11: Si el trabajador esta en el sistema publico de pensiones, se le descuenta el 13% de todo lo que gano. Si esta en una AFP, esta fila queda en 0.00. | D11: No aplica en el Caso 3 (esta en AFP): 0.00
A12: AFP fondo | B12: IF(Sistema = "AFP", ROUND(Total remuneraciones x 10%, 2), 0) | C12: El aporte que va a la cuenta individual del trabajador. Es ahorro suyo: no se pierde, es lo que financiara su pension. | D12: 3,253.00 x 10% = 325.30
A13: AFP comision | B13: IF(Sistema = "AFP", ROUND(Total remuneraciones x 1.60%, 2), 0) | C13: Lo que cobra la AFP por administrar el fondo. Este si es costo: no vuelve al trabajador. | D13: 3,253.00 x 1.60% = 52.048, redondeado 52.05
A14: AFP seguro | B14: IF(Sistema = "AFP", ROUND(Total remuneraciones x 1.35%, 2), 0) | C14: Prima del seguro de invalidez y sobrevivencia. Tambien es costo. | D14: 3,253.00 x 1.35% = 43.9155, redondeado 43.92
A15: Adelantos | B15: ROUND(Monto ingresado, 2) | C15: Dinero que el trabajador ya recibio antes de la fecha de pago. Se resta tal cual, sin ningun calculo. | D15: 200.00
... A18: EsSalud | B18: ROUND(Total remuneraciones x 9%, 2) | C18: Aporte al seguro de salud que paga el EMPLEADOR, no el trabajador. Aparece en la boleta en la tercera columna para mostrar el costo real de la empresa, pero nunca se descuenta del neto. | D18: 3,253.00 x 9% = 292.77
A20: RESPUESTAS A LAS PREGUNTAS DE ANALISIS
A21: 1. ONP o AFP | B21: Con los datos del Caso 3, el neto con ONP es 2,630.11 y con AFP Ejemplo es 2,631.73: la AFP deja S/ 1.62 mas este mes, porque sus tres tasas suman 12.95% contra el 13% de la ONP. Comparar porcentajes no basta: el 10% del fondo AFP va a la cuenta individual del trabajador, o sea sigue siendo su dinero, mientras que comision y seguro son costo puro. La ONP, en cambio, es un fondo comun que exige 20 anos de aportes para dar pension: quien aporta menos tiempo puede quedarse sin nada. La decision depende de la edad, los anos que falten para jubilarse y la rentabilidad del fondo, no del neto de un mes.
A22: 2. Costo real para la empresa | B22: En el Caso 3 el trabajador le cuesta a la empresa 3,253.00 de remuneraciones mas 292.77 de EsSalud = S/ 3,545.77. De ese costo, al trabajador le llega 2,631.73 como neto, es decir el 74.22%. Si se considera que los 200.00 de adelanto ya los habia recibido, lo que percibe en el mes equivale al 79.86%. La diferencia se reparte entre su propio fondo de pension, las comisiones de la AFP y el seguro de salud.
A23: 3. Dias laborados | B23: En el Caso 2, con 27 dias el neto es 1,516.41; con los 30 dias seria 1,673.01. La diferencia en el bruto es 180.00 pero en el neto solo 156.60, exactamente el 87%. La razon es que la ONP se queda con el 13% de ese incremento: cada sol adicional de remuneracion llega al bolsillo descontado. Ademas la asignacion familiar no cambia, porque es un monto fijo que no depende de los dias trabajados.
A24: 4. Horas extras | B24: En el Caso 3 las horas extras suman 62.50 + 67.50 = 130.00 sobre un total de remuneraciones de 3,253.00, o sea el 4.00%. Son 8 horas de sobretiempo que apenas mueven el total, aunque se paguen con recargo.
A25: 5. Con datos reales | B25: Cada integrante toma un sueldo de una oferta laboral publicada, guarda el enlace y la fecha de consulta, y arma su boleta en la hoja Casos. Luego compara que porcentaje del bruto llega al trabajador con el de dos companeros que usaron otros sueldos. El sueldo debe ser igual o mayor que la RMV y las personas y empresas son ficticias.
